{

  "footer": [
    {
      "name": "Головне",
      "menu": [
        {
          "text": "Вартість",
          "url": "/order"
        }
      ]
    },
    {
      "name": "Продукти та послуги",
      "menu": [
        {
          "text": "Онлайн курс «Здорова стопа»",
          "url": "#"
        },
        {
          "text": "СК «АСАМБЛЕ»",
          "url": "https://www.instagram.com/rg.asamble/"
        }
      ]
    },
    {
      "name": "Допомога",
      "menu": [
        {
          "text": "Правила повернення грошових коштів",
          "url": "/refund"
        },
        {
          "text": "Договір публічної оферти",
          "url": "/offerta"
        }
      ]
    }
  ]
}
